amazon_efs/Efs.py
amazon_efs/__init__.py
amazon_efs/common/EfsUtils.py
amazon_efs/common/__init__.py
amazon_efs/common/general.py
amazon_efs/compute_env/AbstractComputeEnv.py
amazon_efs/compute_env/BatchComputeEnv.py
amazon_efs/compute_env/LambdaComputeEnv.py
amazon_efs/compute_env/__init__.py
amazon_efs/type/EfsOptions.py
amazon_efs/type/__init__.py
amazon_efs-0.4.0.dist-info/METADATA
amazon_efs-0.4.0.dist-info/WHEEL
amazon_efs-0.4.0.dist-info/top_level.txt
amazon_efs-0.4.0.dist-info/RECORD
