Metadata-Version: 2.1
Name: amazon-efs
Version: 0.4.0
Summary: Amazon EFS (amazon-efs) allows programmatically manipulate EFS data (create, read, delete, list files) from any machine.
Home-page: https://github.com/kankou-aliaksei/amazon-efs
Author: Aliaksei Kankou
Author-email: aliaksei.kankou@gmail.com
Project-URL: Bug Tracker, https://github.com/kankou-aliaksei/amazon-efs/issues
Requires-Python: >=3.6
Provides-Extra: boto3
Requires-Dist: boto3 (>=1.24.50) ; extra == 'boto3'
